formate_black/__init__.py
formate_black/py.typed
formate_black-0.2.0.post1.dist-info/LICENSE
formate_black-0.2.0.post1.dist-info/METADATA
formate_black-0.2.0.post1.dist-info/WHEEL
formate_black-0.2.0.post1.dist-info/entry_points.txt
formate_black-0.2.0.post1.dist-info/RECORD
