Metadata-Version: 2.1
Name: formate-black
Version: 0.2.0.post1
Summary: Use black with formate.
Author-email: Dominic Davis-Foster <dominic@davis-foster.co.uk>
License: MIT
Keywords: black,formate,formatting,linting
Home-page: https://github.com/python-formate/formate-black
Project-URL: Issue Tracker, https://github.com/python-formate/formate-black/issues
Project-URL: Source Code, https://github.com/python-formate/formate-black
Platform: Windows
Platform: macOS
Platform: Linux
Classifier: Development Status :: 4 - Beta
Classifier: Environment :: Console
Classifier: Intended Audience :: Developers
Classifier: License :: OSI Approved :: MIT License
Classifier: Operating System :: OS Independent
Classifier: Programming Language :: Python
Classifier: Programming Language :: Python :: 3 :: Only
Classifier: Programming Language :: Python :: 3.6
Classifier: Programming Language :: Python :: 3.7
Classifier: Programming Language :: Python :: 3.8
Classifier: Programming Language :: Python :: 3.9
Classifier: Programming Language :: Python :: 3.10
Classifier: Programming Language :: Python :: 3.11
Classifier: Programming Language :: Python :: 3.12
Classifier: Programming Language :: Python :: Implementation :: CPython
Classifier: Typing :: Typed
Requires-Python: >=3.6
Requires-Dist: black<22.1.0,>=21.5b1
Requires-Dist: domdf-python-tools>=2.9.1
Requires-Dist: formate>=0.4.4
